{
  "smooth": 1085,
  "stone": 1005,
  "wood": 700,
  "dark": 610,
  "tiles": 545,
  "metal": 505,
  "white": 485,
  "floor": 470,
  "paving": 465,
  "wall": 440,
  "brown": 425,
  "light": 415,
  "planks": 390,
  "gray": 385,
  "rough": 375,
  "old": 345,
  "black": 340,
  "cloth": 330,
  "brick": 285,
  "paint": 280,
  "red": 265,
  "ground": 265,
  "blue": 245,
  "yellow": 245,
  "pattern": 245,
  "dirt": 245,
  "gravel": 235,
  "green": 230,
  "rock": 220,
  "road": 210,
  "orange": 205,
  "rocks": 195,
  "asphalt": 190,
  "marble": 185,
  "cliff": 175,
  "modern": 170,
  "concrete": 165,
  "square": 165,
  "scratches": 160,
  "danger": 160,
  "plaster": 150,
  "moss": 140,
  "flat": 135,
  "leather": 135,
  "rust": 135,
  "sign": 130,
  "beige": 125,
  "carpet": 115,
  "woven": 100,
  "nails": 100,
  "facade": 90,
  "reflective": 90,
  "broken": 85,
  "sludge": 80,
  "sand": 80,
  "tree": 75,
  "small": 75,
  "bump": 75,
  "silver": 75,
  "lines": 75,
  "mortar": 70,
  "patches": 70,
  "plastic": 70,
  "forest": 65,
  "sloppy": 65,
  "smear": 65,
  "walkway": 65,
  "interlocking": 65,
  "terrazzo": 65,
  "bathroom": 65,
  "crack": 60,
  "medical": 60,
  "glass": 60,
  "mud": 60,
  "desert": 60,
  "hexagonal": 60,
  "subway": 60,
  "industrial": 55,
  "building": 55,
  "night": 55,
  "window": 55,
  "nailed": 55,
  "bark": 50,
  "christmas": 50,
  "plain": 50,
  "bright": 50,
  "cyan": 50,
  "weave": 50,
  "fence": 50,
  "perforated": 50,
  "pool": 50,
  "tiling": 50,
  "mosaic": 50,
  "river": 45,
  "leaf": 45,
  "leaves": 45,
  "plates": 45,
  "cobblestone": 45,
  "siding": 45,
  "surface": 40,
  "leaks": 40,
  "marking": 40,
  "markings": 40,
  "antique": 40,
  "rotated": 40,
  "tilted": 40,
  "processed": 40,
  "grunge": 40,
  "used": 35,
  "paper": 35,
  "sci": 35,
  "computer": 35,
  "chip": 35,
  "fi": 35,
  "motherboard": 35,
  "ornament": 35,
  "wool": 35,
  "wet": 35,
  "brushed": 35,
  "spots": 35,
  "car": 35,
  "foam": 30,
  "sponge": 30,
  "vintage": 30,
  "city": 30,
  "clay": 30,
  "uniform": 30,
  "bunker": 30,
  "diamond": 30,
  "skyscraper": 30,
  "windows": 30,
  "mesh": 30,
  "wire": 30,
  "wireless": 30,
  "fingerprints": 30,
  "water": 30,
  "fire": 30,
  "leaking": 30,
  "trusted": 30,
  "decoration": 30,
  "design": 30,
  "deal": 30,
  "snow": 30,
  "wicket": 30,
  "rug": 25,
  "stripes": 25,
  "plank": 25,
  "corrugated": 25,
  "lime": 25,
  "beach": 25,
  "ice": 25,
  "volcano": 25,
  "lava": 25,
  "magma": 25,
  "moisture": 25,
  "streaks": 25,
  "couch": 25,
  "sofa": 25,
  "bronze": 25,
  "round": 25,
  "slate": 25,
  "roofing": 25,
  "winter": 25,
  "contrast": 25,
  "damaged": 20,
  "cardboard": 20,
  "mat": 20,
  "checker": 20,
  "knight": 20,
  "chainmail": 20,
  "raw": 20,
  "rectangle": 20,
  "vest": 20,
  "substance": 20,
  "polyester": 20,
  "grass": 20,
  "frozen": 20,
  "lake": 20,
  "erosion": 20,
  "grid": 20,
  "industry": 20,
  "pipe": 20,
  "mountain": 20,
  "uneven": 20,
  "sheets": 20,
  "hole": 20,
  "sheet": 20,
  "stamped": 20,
  "holes": 20,
  "imperfections": 20,
  "panel": 20,
  "solar": 20,
  "sun": 20,
  "cell": 20,
  "kitchen": 20,
  "acoustic": 15,
  "happening": 15,
  "sound": 15,
  "new": 15,
  "cane": 15,
  "sugar": 15,
  "candy": 15,
  "coating": 15,
  "cupboard": 15,
  "plywood": 15,
  "ball": 15,
  "sphere": 15,
  "star": 15,
  "cast": 15,
  "screws": 15,
  "plate": 15,
  "perfection": 15,
  "finger": 15,
  "print": 15,
  "ocean": 15,
  "sea": 15,
  "soap": 15,
  "pebble": 15,
  "sticks": 15,
  "soil": 15,
  "cuffs": 15,
  "covered": 15,
  "powder": 15,
  "roman": 15,
  "card": 15,
  "credit": 15,
  "debit": 15,
  "payment": 15,
  "arrow": 15,
  "rope": 15,
  "string": 15,
  "skull": 15,
  "bones": 15,
  "skulls": 15,
  "bone": 15,
  "toxic": 15,
  "hazard": 15,
  "tactile": 15,
  "blind": 15,
  "sidewalk": 15,
  "tape": 15,
  "police": 15,
  "sandstone": 10,
  "church": 10,
  "rustic": 10,
  "torn": 10,
  "mold": 10,
  "stuffed": 10,
  "towel": 10,
  "bed": 10,
  "rocky": 10,
  "autumn": 10,
  "path": 10,
  "pathway": 10,
  "gold": 10,
  "copper": 10,
  "eroded": 10,
  "erode": 10,
  "cross": 10,
  "parking": 10,
  "dust": 10,
  "left": 10,
  "straight": 10,
  "boulder": 10,
  "house": 10,
  "mark": 10,
  "exclamation": 10,
  "general": 10,
  "biohazard": 10,
  "genetic": 10,
  "irritant": 10,
  "radiation": 10,
  "high": 10,
  "temperature": 10,
  "hot": 10,
  "cherry": 10,
  "subtle": 10,
  "greysmall": 5,
  "dots": 5,
  "points": 5,
  "holidays": 5,
  "waves": 5,
  "bare": 5,
  "jeans": 5,
  "carbon": 5,
  "fiber": 5,
  "sci-fi": 5,
  "chair": 5,
  "felt": 5,
  "variety": 5,
  "sandy": 5,
  "hard": 5,
  "tracks": 5,
  "tire": 5,
  "fall": 5,
  "dead": 5,
  "dry": 5,
  "branches": 5,
  "sewage": 5,
  "leak": 5,
  "rain": 5,
  "skin": 5,
  "snake": 5,
  "crocodile": 5,
  "cover": 5,
  "mantle": 5,
  "scratch": 5,
  "reflection": 5,
  "aid": 5,
  "first": 5,
  "bumps": 5,
  "patronage": 5,
  "created": 5,
  "minimalist": 5,
  "arches": 5,
  "arch": 5,
  "shape": 5,
  "gobble": 5,
  "bike": 5,
  "bicycle": 5,
  "bus": 5,
  "stick": 5,
  "man": 5,
  "human": 5,
  "person": 5,
  "walking": 5,
  "spike": 5,
  "cave": 5,
  "detailed": 5,
  "sharp": 5,
  "edges": 5,
  "irregular": 5,
  "roof": 5,
  "bio": 5,
  "slippery": 5,
  "atomic": 5,
  "materials": 5,
  "flammable": 5,
  "voltage": 5,
  "electricity": 5,
  "freezing": 5,
  "low": 5,
  "laser": 5,
  "for": 5,
  "falling": 5,
  "objects": 5,
  "watch": 5,
  "temperatures": 5,
  "warm": 5,
  "gears": 5,
  "parts": 5,
  "rotating": 5,
  "truck": 5,
  "trucks": 5,
  "forklift": 5,
  "explosion": 5,
  "risk": 5,
  "entrapment": 5,
  "overhead": 5,
  "crane": 5,
  "biology": 5,
  "apocalypse": 5,
  "hazardous": 5,
  "environment": 5,
  "fish": 5,
  "the": 5,
  "to": 5,
  "fluffy": 5,
  "fresh": 5,
  "steps": 5,
  "stopped": 5,
  "cold": 5,
  "outdoor": 5,
  "large": 5,
  "hex": 5,
  "shower": 5,
  "end": 5,
  "log": 5,
  "pale": 5,
  "knotholes": 5,
  "stripped": 5,
  "playground": 5,
  "chips": 5,
  "random": 5
}